README.md
setup.py
espresso/__init__.py
espresso/core.py
espresso/websockets/client.py
espresso/websockets/protocol.py
micropython_espresso.egg-info/PKG-INFO
micropython_espresso.egg-info/SOURCES.txt
micropython_espresso.egg-info/dependency_links.txt
micropython_espresso.egg-info/top_level.txt