Metadata-Version: 1.2
Name: micropython-espresso
Version: 1.14
Summary: Micropython scripts for Espresso IDE.
Home-page: http://yeisoncardona.com/
Author: Yeison Cardona
Author-email: yeisoneng@gmail.com
Maintainer: Yeison Cardona
Maintainer-email: yeisoneng@gmail.com
License: GNU GPL
Download-URL: https://bitbucket.org/espressoide/micropython-espresso/downloads/
Platform: UNKNOWN
